flytekitplugins_flyin-1.10.3-py3.12-nspkg.pth
flytekitplugins/flyin/__init__.py
flytekitplugins/flyin/utils.py
flytekitplugins/flyin/jupyter_lib/__init__.py
flytekitplugins/flyin/jupyter_lib/constants.py
flytekitplugins/flyin/jupyter_lib/decorator.py
flytekitplugins/flyin/vscode_lib/__init__.py
flytekitplugins/flyin/vscode_lib/config.py
flytekitplugins/flyin/vscode_lib/constants.py
flytekitplugins/flyin/vscode_lib/decorator.py
flytekitplugins_flyin-1.10.3.dist-info/METADATA
flytekitplugins_flyin-1.10.3.dist-info/WHEEL
flytekitplugins_flyin-1.10.3.dist-info/entry_points.txt
flytekitplugins_flyin-1.10.3.dist-info/namespace_packages.txt
flytekitplugins_flyin-1.10.3.dist-info/top_level.txt
flytekitplugins_flyin-1.10.3.dist-info/RECORD
